gedcom7/__init__.py
gedcom7/cast.py
gedcom7/const.py
gedcom7/grammar.py
gedcom7/parser.py
gedcom7/types.py
gedcom7/util.py
gedcom7-0.4.0.dist-info/licenses/LICENSE
gedcom7-0.4.0.dist-info/METADATA
gedcom7-0.4.0.dist-info/WHEEL
gedcom7-0.4.0.dist-info/top_level.txt
gedcom7-0.4.0.dist-info/RECORD
