Metadata-Version: 2.4
Name: gedcom7
Version: 0.4.0
Summary: GEDCOM 7 parser
Home-page: https://github.com/DavidMStraub/python-gedcom7
Author: David M. Straub
Author-email: straub@protonmail.com
License: MIT
License-File: LICENSE
Dynamic: license-file
